{"name":"Libgatey","tagline":"Visualize and control C++ data using the web browser. Single hpp/cpp, no dependencies, OS X, Windows, Linux.","body":"libgateY\r\n========\r\n\r\nVisualize and control C++ data using the web browser. Single hpp/cpp, no dependencies, OS X, Windows, Linux.\r\n\r\nSimple example:\r\n\r\nC++\r\n\r\n#include \"../../gatey.hpp\"\r\n#include <thread>\r\n#include <chrono>\r\n#include <cmath>\r\n\r\nint main() {\r\n\tstd::chrono::milliseconds dura(20);\r\n\tgatey::global = std::make_shared<gatey::GateY>();\r\n\t\r\n\tgatey::WriteVariable<std::tuple<float, float>> gF(\"y\");\r\n\tgatey::ReadVariable<float> gDt(\"dt\", 0.01f);\r\n\tgatey::ReadVariable<float> gC(\"c\", 1.0f);\r\n\r\n\r\n\tfloat time = 0.0f;\r\n\twhile (true) {\r\n\t\tfloat y = gC.get() * std::sin(time);\r\n\t\tgF.set(std::make_pair(time, y));\r\n\t\ttime += gDt.get();\r\n\t\tstd::this_thread::sleep_for(dura);\r\n\t}\r\n\r\n    return 0;\r\n}\r\n\r\nJavaScript\r\n\r\n<!DOCTYPE html>\r\n<meta charset=\"utf-8\">\r\n<html>\r\n<body>\r\n<link href=\"http://code.jquery.com/ui/1.11.0/themes/smoothness/jquery-ui.min.css\" rel=\"stylesheet\" type=\"text/css\" />\r\n<script src=\"http://code.jquery.com/jquery-1.11.0.min.js\"></script>\r\n<script src=\"http://code.jquery.com/ui/1.11.0/jquery-ui.min.js\"></script>\r\n<script src=\"gateY.js\"></script>\r\n<script>\r\n    \"use strict\";\r\n\r\n    var gDt, gC, gY;\r\n\r\n    function refresh() {\r\n        gC.set($(\"#slider_c\").slider(\"value\") / 100);\r\n        gDt.set($(\"#slider_dt\").slider(\"value\") / 1000)\r\n    }\r\n\r\n    $(function() {\r\n        $('#slider_dt').slider({\r\n            min: 0, max: 100, value: 1,\r\n            slide: refresh,\r\n            change: refresh\r\n        });\r\n\r\n        $('#slider_c').slider({\r\n            min: 0, max: 100, value: 1,\r\n            slide: refresh,\r\n            change: refresh\r\n        });\r\n    });\r\n\r\n    $(document).ready(function() {\r\n\r\n        gDt = new gatey.WriteVariable('dt');\r\n        gC = new gatey.WriteVariable('c');\r\n        gY = new gatey.ReadVariable('y', 0);\r\n\r\n        gY.onChange = function(xs) {\r\n            $('#y').html(JSON.stringify(xs));\r\n        };\r\n    });\r\n</script>\r\n<div id=\"slider_dt\"></div>\r\n<div id=\"slider_c\"></div>\r\n<h1 id=\"y\"></h1>\r\n</body>\r\n</html>\r\n","google":"","note":"Don't delete this file! It's used internally to help with page regeneration."}